coda_mcp/__init__.py
coda_mcp/coda_client.py
coda_mcp/logging.py
coda_mcp/rate_limiter.py
coda_mcp/server.py
coda_mcp/cli/__init__.py
coda_mcp/cli/configure_clients.py
coda_mcp/cli/mcpctl.py
coda_mcp/memory/__init__.py
coda_mcp/memory/event_log.py
coda_mcp/memory/knowledge_graph.py
coda_mcp/memory/profiles.py
coda_mcp/memory/trace.py
coda_mcp/resources/__init__.py
coda_mcp/resources/error_handlers.py
coda_mcp/resources/formatters.py
coda_mcp/resources/truncation.py
coda_mcp/tools/__init__.py
coda_mcp/tools/account.py
coda_mcp/tools/analytics.py
coda_mcp/tools/automations.py
coda_mcp/tools/categories.py
coda_mcp/tools/controls.py
coda_mcp/tools/documents.py
coda_mcp/tools/formulas.py
coda_mcp/tools/pages.py
coda_mcp/tools/permissions.py
coda_mcp/tools/rows.py
coda_mcp/tools/tables.py
coda_mcp/tools/webhooks.py
coda_mcp-0.12.0.dist-info/licenses/LICENSE
coda_mcp-0.12.0.dist-info/METADATA
coda_mcp-0.12.0.dist-info/WHEEL
coda_mcp-0.12.0.dist-info/entry_points.txt
coda_mcp-0.12.0.dist-info/top_level.txt
coda_mcp-0.12.0.dist-info/RECORD
