Metadata-Version: 2.4
Name: coda-mcp
Version: 0.12.0
Summary: MCP server for Coda document integration
Author-email: Liminal Commons <team@liminalcommons.org>
License: MIT
Project-URL: Homepage, https://github.com/liminalcommons/mcp-server-coda
Project-URL: Documentation, https://github.com/liminalcommons/mcp-server-coda/tree/main/docs
Project-URL: Repository, https://github.com/liminalcommons/mcp-server-coda.git
Project-URL: Issues, https://github.com/liminalcommons/mcp-server-coda/issues
Keywords: mcp,coda,model-context-protocol,ai,integration
Classifier: Development Status :: 4 - Beta
Classifier: Intended Audience :: Developers
Classifier: License :: OSI Approved :: MIT License
Classifier: Programming Language :: Python :: 3
Classifier: Programming Language :: Python :: 3.11
Classifier: Programming Language :: Python :: 3.12
Requires-Python: >=3.11
License-File: LICENSE
Requires-Dist: pydantic>=2.7
Requires-Dist: mcp==1.13.1
Requires-Dist: codaio>=0.6.0
Requires-Dist: httpx>=0.24.0
Requires-Dist: pyyaml>=6.0
Provides-Extra: dev
Requires-Dist: pytest>=8.0; extra == "dev"
Requires-Dist: pytest-anyio>=0.0.0; extra == "dev"
Requires-Dist: pytest-docker>=3.1.0; extra == "dev"
Requires-Dist: pytest-timeout>=2.2.0; extra == "dev"
Requires-Dist: pytest-cov>=4.1.0; extra == "dev"
Requires-Dist: pytest-bdd>=7.0.0; extra == "dev"
Requires-Dist: hypothesis>=6.100.0; extra == "dev"
Requires-Dist: requests>=2.31.0; extra == "dev"
Requires-Dist: responses>=0.24.0; extra == "dev"
Requires-Dist: jsonschema>=4.21.0; extra == "dev"
Provides-Extra: security
Requires-Dist: pip-audit>=2.0; extra == "security"
Requires-Dist: bandit>=1.7; extra == "security"
Requires-Dist: ruff>=0.1; extra == "security"
Requires-Dist: cyclonedx-bom>=4.0; extra == "security"
Dynamic: license-file
